pyMemoryGame/__init__.py
pyMemoryGame/filech.py
pyMemoryGame/highscore_database.py
pyMemoryGame/highscore_screen.py
pyMemoryGame/main.py
pyMemoryGame/memory_screen.py
pyMemoryGame/picture_viewer.py
pyMemoryGame/school.ini
pyMemoryGame/school.kv
pyMemoryGame/utils.py
pyMemoryGame/video_player.py
pyMemoryGame/icons/apply.png
pyMemoryGame/icons/back.png
pyMemoryGame/icons/highscores.png
pyMemoryGame/icons/home.png
pyMemoryGame/icons/memory.png
pyMemoryGame/icons/pictures.png
pyMemoryGame/icons/play.png
pyMemoryGame/icons/reset.png
pyMemoryGame/icons/settings.png
pyMemoryGame/icons/shuffle.png
pyMemoryGame/icons/stop.png
pyMemoryGame/icons/video.png
pyMemoryGame/memory_cards/bat.png
pyMemoryGame/memory_cards/broom.png
pyMemoryGame/memory_cards/candle.png
pyMemoryGame/memory_cards/cat.png
pyMemoryGame/memory_cards/cobweb.png
pyMemoryGame/memory_cards/ghost.png
pyMemoryGame/memory_cards/gravestone.png
pyMemoryGame/memory_cards/moon.png
pyMemoryGame/memory_cards/owl.png
pyMemoryGame/memory_cards/pumpkin.png
pyMemoryGame/pictures/README
pyMemoryGame/videos/README
pyMemoryGame_t_tibor-0.1.0.dist-info/LICENSE
pyMemoryGame_t_tibor-0.1.0.dist-info/METADATA
pyMemoryGame_t_tibor-0.1.0.dist-info/WHEEL
pyMemoryGame_t_tibor-0.1.0.dist-info/entry_points.txt
pyMemoryGame_t_tibor-0.1.0.dist-info/top_level.txt
pyMemoryGame_t_tibor-0.1.0.dist-info/RECORD
