Metadata-Version: 2.1
Name: pyMemoryGame-t-tibor
Version: 0.1.0
Summary: A simple memory game implemented with kivy.
Home-page: https://github.com/t-tibor/pyMemoryGame
Author: Tusori Tibor
Author-email: ttuti94@gmail.com
License: UNKNOWN
Platform: UNKNOWN
Classifier: Programming Language :: Python :: 3
Classifier: License :: OSI Approved :: MIT License
Classifier: Operating System :: OS Independent
Requires-Python: >=3.6
Requires-Dist: docutils
Requires-Dist: pygments
Requires-Dist: pypiwin32
Requires-Dist: kivy-deps.sdl2 (==0.1.*)
Requires-Dist: kivy-deps.glew (==0.1.*)
Requires-Dist: kivy-deps.angle (==0.1.*)
Requires-Dist: ffpyplayer (==4.3.1)
Requires-Dist: kivy (==1.11.1)
Requires-Dist: kivy-examples (==1.11.1)
